quantumflow/__init__.py
quantumflow/cli.py
quantumflow/config.py
quantumflow/core.py
quantumflow/execution.py
quantumflow/metrics.py
quantumflow/validation.py
python_quantumflow-2.0.3.dist-info/METADATA
python_quantumflow-2.0.3.dist-info/WHEEL
python_quantumflow-2.0.3.dist-info/top_level.txt
python_quantumflow-2.0.3.dist-info/RECORD
