Metadata-Version: 2.4
Name: python-quantumflow
Version: 2.0.3
Summary: Python QuantumFlow: Advanced type conversion for Python
Home-page: https://github.com/magi8101/python-quantumflow
Author: Magi Sharma
Author-email: magi@example.com
Classifier: Programming Language :: Python :: 3
Classifier: License :: OSI Approved :: MIT License
Classifier: Operating System :: OS Independent
Classifier: Development Status :: 5 - Production/Stable
Classifier: Intended Audience :: Developers
Classifier: Topic :: Software Development :: Libraries :: Python Modules
Requires-Python: >=3.7
Dynamic: author
Dynamic: author-email
Dynamic: classifier
Dynamic: description
Dynamic: description-content-type
Dynamic: home-page
Dynamic: requires-python
Dynamic: summary
